FicImageScript/__init__.py
FicImageScript/image.py
FicImageScript/main.py
FicImageScript/utils.py
FicImageScript-4.1.1.dist-info/LICENSE
FicImageScript-4.1.1.dist-info/METADATA
FicImageScript-4.1.1.dist-info/WHEEL
FicImageScript-4.1.1.dist-info/entry_points.txt
FicImageScript-4.1.1.dist-info/top_level.txt
FicImageScript-4.1.1.dist-info/RECORD
