Metadata-Version: 2.1
Name: FicImageScript
Version: 4.1.1
Summary: FicImage is an application designed to enhance the reading experience of FicHub epubs.
Author-email: "Emmanuel C. Jemeni" <jemenichinonso11@gmail.com>
License: MIT License
Project-URL: Homepage, https://github.com/Jemeni11/FicImage
Project-URL: Bug Tracker, https://github.com/Jemeni11/FicImage/issues
Keywords: fanfiction,fichub,ficimage,image
Classifier: Development Status :: 5 - Production/Stable
Classifier: Programming Language :: Python :: 3
Classifier: License :: OSI Approved :: MIT License
Classifier: Operating System :: OS Independent
Classifier: Topic :: Internet :: WWW/HTTP
Requires-Python: >=3.6
License-File: LICENSE
Requires-Dist: beautifulsoup4 >=4.12.2
Requires-Dist: certifi >=2022.12.7
Requires-Dist: charset-normalizer >=3.1.0
Requires-Dist: EbookLib >=0.18
Requires-Dist: idna >=3.4
Requires-Dist: lxml >=4.9.2
Requires-Dist: Pillow >=9.5.0
Requires-Dist: requests >=2.31.0
Requires-Dist: six >=1.16.0
Requires-Dist: soupsieve >=2.4.1
Requires-Dist: urllib3 >=1.26.15
